machinery/__init__.py
machinery/machinery.py
machinery/backend/__init__.py
machinery/backend/mongodb.py
machinery/broker/__init__.py
machinery/broker/redis.py
pymachinery-0.1.3.dist-info/LICENSE
pymachinery-0.1.3.dist-info/METADATA
pymachinery-0.1.3.dist-info/WHEEL
pymachinery-0.1.3.dist-info/top_level.txt
pymachinery-0.1.3.dist-info/RECORD
