Metadata-Version: 2.1
Name: pymachinery
Version: 0.1.3
Summary: Python workers for RichardKnop/machinery
Home-page: https://github.com/nmcapule/pymachinery
Author: Nathaniel M. Capule
Author-email: nmcapule@gmail.com
License: UNKNOWN
Platform: UNKNOWN
Classifier: Programming Language :: Python :: 3
Classifier: License :: OSI Approved :: MIT License
Classifier: Operating System :: OS Independent
Requires-Python: >=3.6
Requires-Dist: pymongo
Requires-Dist: redis
